{
  "background_u_index": 0,
  "background_v_index": 0,
  "category": "focus",
  "description": "book.minejago.wiki.focus.using.description",
  "hide_while_locked": false,
  "icon": {
    "height": 32,
    "texture": "minejago:textures/modonomicon/wiki/spinjitzu/spinjitzu.png",
    "width": 32
  },
  "name": "book.minejago.wiki.focus.using.name",
  "pages": [
    {
      "type": "modonomicon:text",
      "anchor": "spinjitzu",
      "condition": {
        "type": "modonomicon:none"
      },
      "show_title_separator": true,
      "text": "book.minejago.wiki.focus.using.spinjitzu.text",
      "title": "book.minejago.wiki.focus.using.spinjitzu.title",
      "use_markdown_in_title": false
    },
    {
      "type": "modonomicon:text",
      "anchor": "dragon",
      "condition": {
        "type": "modonomicon:none"
      },
      "show_title_separator": true,
      "text": "book.minejago.wiki.focus.using.dragon.text",
      "title": "book.minejago.wiki.focus.using.dragon.title",
      "use_markdown_in_title": false
    },
    {
      "type": "modonomicon:text",
      "anchor": "golden_weapon",
      "condition": {
        "type": "modonomicon:none"
      },
      "show_title_separator": true,
      "text": "book.minejago.wiki.focus.using.golden_weapon.text",
      "title": "book.minejago.wiki.focus.using.golden_weapon.title",
      "use_markdown_in_title": false
    },
    {
      "type": "modonomicon:text",
      "anchor": "insomnia",
      "condition": {
        "type": "modonomicon:none"
      },
      "show_title_separator": true,
      "text": "book.minejago.wiki.focus.using.insomnia.text",
      "title": "book.minejago.wiki.focus.using.insomnia.title",
      "use_markdown_in_title": false
    }
  ],
  "show_when_any_parent_unlocked": false,
  "sort_number": 0,
  "x": 0,
  "y": 0
}